sfbulkapiv2/__init__.py
sfbulkapiv2/__version__.py
sfbulkapiv2/bulk.py
sfbulkapiv2-0.0.3.dist-info/LICENSE.txt
sfbulkapiv2-0.0.3.dist-info/METADATA
sfbulkapiv2-0.0.3.dist-info/WHEEL
sfbulkapiv2-0.0.3.dist-info/top_level.txt
sfbulkapiv2-0.0.3.dist-info/RECORD
