Metadata-Version: 2.1
Name: sfbulkapiv2
Version: 0.0.3
Summary: A simple Salesforce bulk API v2 cliente
Home-page: https://github.com/mar-ben/salesforce-bulkv2
Author: Example Author
Author-email: mailbenhar@gmail.com
License: UNKNOWN
Project-URL: Bug Tracker, https://github.com/mar-ben/salesforce-bulkv2/issues
Platform: UNKNOWN
Classifier: Programming Language :: Python :: 3
Classifier: License :: OSI Approved :: MIT License
Classifier: Operating System :: OS Independent
Requires-Python: >=3.6
License-File: LICENSE.txt
